pysteganography/__init__.py
pysteganography/stegano.py
pysteganography-0.1.0.dist-info/LICENSE.txt
pysteganography-0.1.0.dist-info/METADATA
pysteganography-0.1.0.dist-info/WHEEL
pysteganography-0.1.0.dist-info/top_level.txt
pysteganography-0.1.0.dist-info/RECORD
